[
  {
    "nome": "tabata",
    "email": "tabata.bertazzo@gmail.com",
    "segmento": "moda",
    "produto": "moda",
    "publico": "moda",
    "problema": "moda",
    "solucao": "moda",
    "canal": "Instagram",
    "tipo": "Publicação textual",
    "dataHora": "2025-03-21T18:48:02.245Z",
    "recebidoEm": "2025-03-21T18:48:02.267Z"
  },
  {
    "nome": "tabata",
    "email": "tabata.bertazzo@gmail.com",
    "segmento": "moda",
    "produto": "moda",
    "publico": "moda",
    "problema": "moda",
    "solucao": "moda",
    "canal": "Instagram",
    "tipo": "Publicação textual",
    "dataHora": "2025-03-21T18:59:20.839Z",
    "recebidoEm": "2025-03-21T18:59:20.845Z"
  },
  {
    "nome": "teste 2",
    "email": "tabata.bertazzo@gmail.com",
    "segmento": "moda",
    "produto": "moda",
    "publico": "moda",
    "problema": "moda",
    "solucao": "moda",
    "canal": "Instagram",
    "tipo": "Publicação textual",
    "dataHora": "2025-03-21T19:02:00.441Z",
    "recebidoEm": "2025-03-21T19:02:00.447Z"
  },
  {
    "nome": "teste 2",
    "email": "tabata.bertazzo@gmail.com",
    "segmento": "moda",
    "produto": "moda",
    "publico": "moda",
    "problema": "moda",
    "solucao": "moda",
    "canal": "Instagram",
    "tipo": "Publicação textual",
    "dataHora": "2025-03-21T19:03:05.845Z",
    "recebidoEm": "2025-03-21T19:03:05.850Z"
  },
  {
    "nome": "Teste3",
    "email": "tabata.bertazzo@gmail.com",
    "segmento": "moda",
    "produto": "moda",
    "publico": "moda",
    "problema": "moda",
    "solucao": "moda",
    "canal": "Instagram",
    "tipo": "Publicação textual",
    "recebidoEm": "2025-03-21T19:46:28.181Z"
  },
  {
    "nome": "Teste4",
    "email": "tabata.bertazzo@gmail.com",
    "segmento": "moda",
    "produto": "moda",
    "publico": "moda",
    "problema": "moda",
    "solucao": "moda",
    "canal": "Instagram",
    "tipo": "Publicação textual",
    "recebidoEm": "2025-03-21T19:49:02.726Z"
  }
]